rcl/_dummy.cpython-310-x86_64-linux-gnu.so
ros_rcl-10.1.3.data/data/include/rcl/rcl/allocator.h
ros_rcl-10.1.3.data/data/include/rcl/rcl/arguments.h
ros_rcl-10.1.3.data/data/include/rcl/rcl/client.h
ros_rcl-10.1.3.data/data/include/rcl/rcl/context.h
ros_rcl-10.1.3.data/data/include/rcl/rcl/discovery_options.h
ros_rcl-10.1.3.data/data/include/rcl/rcl/domain_id.h
ros_rcl-10.1.3.data/data/include/rcl/rcl/dynamic_message_type_support.h
ros_rcl-10.1.3.data/data/include/rcl/rcl/error_handling.h
ros_rcl-10.1.3.data/data/include/rcl/rcl/event.h
ros_rcl-10.1.3.data/data/include/rcl/rcl/event_callback.h
ros_rcl-10.1.3.data/data/include/rcl/rcl/expand_topic_name.h
ros_rcl-10.1.3.data/data/include/rcl/rcl/graph.h
ros_rcl-10.1.3.data/data/include/rcl/rcl/guard_condition.h
ros_rcl-10.1.3.data/data/include/rcl/rcl/init.h
ros_rcl-10.1.3.data/data/include/rcl/rcl/init_options.h
ros_rcl-10.1.3.data/data/include/rcl/rcl/lexer.h
ros_rcl-10.1.3.data/data/include/rcl/rcl/lexer_lookahead.h
ros_rcl-10.1.3.data/data/include/rcl/rcl/log_level.h
ros_rcl-10.1.3.data/data/include/rcl/rcl/logging.h
ros_rcl-10.1.3.data/data/include/rcl/rcl/logging_rosout.h
ros_rcl-10.1.3.data/data/include/rcl/rcl/macros.h
ros_rcl-10.1.3.data/data/include/rcl/rcl/network_flow_endpoints.h
ros_rcl-10.1.3.data/data/include/rcl/rcl/node.h
ros_rcl-10.1.3.data/data/include/rcl/rcl/node_options.h
ros_rcl-10.1.3.data/data/include/rcl/rcl/node_type_cache.h
ros_rcl-10.1.3.data/data/include/rcl/rcl/publisher.h
ros_rcl-10.1.3.data/data/include/rcl/rcl/rcl.h
ros_rcl-10.1.3.data/data/include/rcl/rcl/remap.h
ros_rcl-10.1.3.data/data/include/rcl/rcl/rmw_implementation_identifier_check.h
ros_rcl-10.1.3.data/data/include/rcl/rcl/security.h
ros_rcl-10.1.3.data/data/include/rcl/rcl/service.h
ros_rcl-10.1.3.data/data/include/rcl/rcl/service_introspection.h
ros_rcl-10.1.3.data/data/include/rcl/rcl/subscription.h
ros_rcl-10.1.3.data/data/include/rcl/rcl/time.h
ros_rcl-10.1.3.dist-info/METADATA
ros_rcl-10.1.3.dist-info/WHEEL
ros_rcl-10.1.3.dist-info/top_level.txt
ros_rcl-10.1.3.dist-info/RECORD
